uniconf/__init__.py
uniconf/convertype.py
uniconf/uniconf.py
UniConf-0.1.2.dist-info/METADATA
UniConf-0.1.2.dist-info/WHEEL
UniConf-0.1.2.dist-info/top_level.txt
UniConf-0.1.2.dist-info/RECORD
