Metadata-Version: 2.1
Name: UniConf
Version: 0.1.2
Summary: A simple module allows you to quickly create and modify a configuration file. Based on 'configparser'.
Home-page: UNKNOWN
Author: Fima20
Author-email: dmitriy2000ms@yandex.ru
License: UNKNOWN
Platform: UNKNOWN
Requires-Dist: configparser
Requires-Dist: datetime
